README.md
setup.py
dozy/__init__.py
dozy/eval.py
dozy/image.py
dozy/nori.py
dozy/utils.py
dozy/video.py
dozy.egg-info/PKG-INFO
dozy.egg-info/SOURCES.txt
dozy.egg-info/dependency_links.txt
dozy.egg-info/top_level.txt
test/test_image.py