Metadata-Version: 1.0
Name: dozy
Version: 0.0.3
Summary: A simple and user-friendly tool for operating images and videos
Home-page: https://github.com/vra/dozy
Author: Yunfeng Wang, Peisen Wang
Author-email: wyf.brz@gmail.com
License: UNKNOWN
Platform: UNKNOWN
